[
    {
        "id": "00:00:00:00:00:0A",
        "serviceName": "Свет на кухне",
        "pin": 47,
        "apin": 5
    },
    {
        "id": "00:00:00:00:01:0A",
        "serviceName": "Свет над столом",
        "pin": 45,
        "apin": 9
    },
    {
        "id": "00:00:00:00:02:0A",
        "serviceName": "Свет над рабочей зоной",
        "pin": 43,
        "apin": 7
    },
    {
        "id": "00:00:00:00:00:0B",
        "serviceName": "Свет в гостинной",
        "pin": 41,
        "apin": 2
    },
    {
        "id": "00:00:00:00:01:0B",
        "serviceName": "LED в гостинной",
        "pin": 39,
        "apin": 3,
        "rgb": {
            "r": 11,
            "g": 13,
            "b": 12
        }
    },
    {
        "id": "00:00:00:00:00:0C",
        "serviceName": "Свет в кладовой",
        "pin": 36,
        "apin": 11
    },
    {
        "id": "00:00:00:00:01:0C",
        "serviceName": "Свет в прихожей",
        "pin": 51,
        "apin": 12
    },
    {
        "id": "00:00:00:00:02:0C",
        "serviceName": "Свет возле лестницы",
        "pin": 34,
        "apin": 15
    },
    {
        "id": "00:00:00:00:03:0C",
        "serviceName": "Свет в коридоре на первом этаже",
        "pin": 53,
        "apin": 13
    },
    {
        "id": "00:00:00:00:00:0D",
        "serviceName": "Свет в коридоре на втором этаже",
        "pin": 50,
        "apin": 18
    },
    {
        "id": "00:00:00:00:00:0E",
        "serviceName": "Свет в коридоре на третьем этаже",
        "pin": 23,
        "apin": 21
    },
    {
        "id": "00:00:00:00:00:0F",
        "serviceName": "Свет в ванной на первом этаже",
        "pin": 28,
        "apin": 8,
        "automations": [
            {
                "id": "00:00:00:02:01:01",
                "condition": {
                    "On": false
                },
                "action": {
                    "On": false
                },
                "timeout": 120000
            },
            {
                "id": "00:00:00:00:01:0F",
                "condition": {
                    "On": false
                },
                "action": {
                    "On": false
                }
            }
        ]
    },
    {
        "id": "00:00:00:00:01:0F",
        "serviceName": "Свет зеркала на первом этаже",
        "pin": 26,
        "apin": 10
    },
    {
        "id": "00:00:00:00:00:10",
        "serviceName": "Свет в ванной на втором этаже",
        "pin": 33,
        "apin": 31,
        "automations": [
            {
                "id": "00:00:00:02:00:00",
                "condition": {
                    "On": false
                },
                "action": {
                    "On": false
                },
                "timeout": 120000
            },
            {
                "id": "00:00:00:00:01:10",
                "condition": {
                    "On": false
                },
                "action": {
                    "On": false
                }
            }
        ]
    },
    {
        "id": "00:00:00:00:01:10",
        "serviceName": "Свет зеркала на втором этаже",
        "pin": 35,
        "apin": 19
    },
    {
        "id": "00:00:00:00:00:11",
        "serviceName": "Свет в кладовой на теретьем этаже",
        "pin": 25,
        "apin": 23
    },
    {
        "id": "00:00:00:00:00:12",
        "serviceName": "Люстра в гостевой",
        "pin": 27,
        "apin": 27
    },
    {
        "id": "00:00:00:00:01:12",
        "serviceName": "Свет в гостевой",
        "pin": 29,
        "apin": 25
    },
    {
        "id": "00:00:00:00:00:13",
        "serviceName": "Люстра в детской",
        "pin": 32,
        "apin": 4
    },
    {
        "id": "00:00:00:00:01:13",
        "serviceName": "Свет в детской ",
        "pin": 30,
        "apin": 6
    },
    {
        "id": "00:00:00:00:00:14",
        "serviceName": "Люстра в спальне ",
        "pin": 48,
        "apin": 29
    },
    {
        "id": "00:00:00:00:01:14",
        "serviceName": "Свет в спальне ",
        "pin": 44,
        "apin": 28
    },
    {
        "id": "00:00:00:00:02:14",
        "serviceName": "Светильник левый",
        "pin": 42,
        "apin": 22
    },
    {
        "id": "00:00:00:00:03:14",
        "serviceName": "Светильник правый",
        "pin": 40,
        "apin": 20
    },
    {
        "id": "00:00:00:00:04:14",
        "serviceName": "Свет в гардеробе",
        "pin": 46,
        "apin": 26
    },
    {
        "id": "00:00:00:00:05:14",
        "serviceName": "Свет на терассе",
        "pin": 38,
        "apin": 24
    }
]
